README.md
setup.cfg
setup.py
ASTFormula.egg-info/PKG-INFO
ASTFormula.egg-info/SOURCES.txt
ASTFormula.egg-info/dependency_links.txt
ASTFormula.egg-info/requires.txt
ASTFormula.egg-info/top_level.txt
astformula/__init__.py
astformula/exceptions.py
astformula/main.py
astformula/defaults/__init__.py
astformula/defaults/functions.py
astformula/defaults/operators.py
astformula/defaults/processors.py