Metadata-Version: 2.1
Name: ASTFormula
Version: 0.0.3
Summary: A simple and extensible AST-based Python formula engine to execute string calculation statements
Home-page: https://github.com/oryba/astformula
Author: Oleh Rybalchenko
Author-email: rv.oleg.ua@gmail.com
License: OSI Approved (BSD)
Download-URL: https://github.com/oryba/astformula/archive/v0.0.3.zip
Platform: UNKNOWN
Classifier: License :: OSI Approved :: BSD License
Classifier: Programming Language :: Python :: 3.5
Classifier: Programming Language :: Python :: 3.6
Classifier: Programming Language :: Python :: 3.7
Classifier: Programming Language :: Python :: 3.8
